discovery30303/__init__.py
discovery30303/py.typed
discovery30303-0.3.2.dist-info/LICENSE
discovery30303-0.3.2.dist-info/METADATA
discovery30303-0.3.2.dist-info/WHEEL
discovery30303-0.3.2.dist-info/RECORD
