Metadata-Version: 2.1
Name: discovery30303
Version: 0.3.2
Summary: Discover devices that respond on port 30303
Home-page: https://github.com/bdraco/discovery30303
Author: J. Nick Koston
Author-email: nick@koston.org
Requires-Python: >=3.8,<4.0
Classifier: Development Status :: 2 - Pre-Alpha
Classifier: Intended Audience :: Developers
Classifier: License :: OSI Approved :: Apache Software License
Classifier: Natural Language :: English
Classifier: Operating System :: OS Independent
Classifier: Programming Language :: Python :: 3
Classifier: Programming Language :: Python :: 3.8
Classifier: Programming Language :: Python :: 3.9
Classifier: Programming Language :: Python :: 3.10
Classifier: Programming Language :: Python :: 3.11
Classifier: Programming Language :: Python :: 3.12
Classifier: Topic :: Software Development :: Libraries
Provides-Extra: docs
Requires-Dist: Sphinx (>=4.0.0,<5.0.0) ; extra == "docs"
Requires-Dist: myst-parser (>=0.16.0,<0.17.0) ; extra == "docs"
Requires-Dist: sphinx-rtd-theme (>=1.0.0,<2.0.0) ; extra == "docs"
Project-URL: Bug Tracker, https://github.com/bdraco/discovery30303/issues
Project-URL: Changelog, https://discovery30303.readthedocs.io/changelog.html
Project-URL: Documentation, https://discovery30303.readthedocs.io
Project-URL: Repository, https://github.com/bdraco/discovery30303
